Metadata-Version: 1.0
Name: ddcafe
Version: 0.0.1
Summary: play "Daydraem cafe" on the terminal.
Home-page: https://github.com/ikorin24/ddcafe
Author: ikorin24
Author-email: sunshinexxab@yahoo.co.jp
License: MIT License
